setup.py
randio/__init__.py
randio/__main__.py
randio/randio.py
randio.egg-info/PKG-INFO
randio.egg-info/SOURCES.txt
randio.egg-info/dependency_links.txt
randio.egg-info/top_level.txt