Metadata-Version: 1.1
Name: randio
Version: 0.1.1
Summary: rtl-sdr radio dongle random number generator
Home-page: UNKNOWN
Author: Michel Pelletier
Author-email: pelletier.michel@yahoo.com
License: MIT License
Platform: UNKNOWN
Classifier: Development Status :: 3 - Alpha
Classifier: Intended Audience :: Developers
Classifier: License :: OSI Approved :: MIT License
Classifier: Operating System :: OS Independent
Classifier: Programming Language :: Python
Classifier: Programming Language :: Python :: 2.7
